pypkgs_ash/__init__.py
pypkgs_ash/pypkgs_ash.py
pypkgs_ash-0.1.0.dist-info/LICENSE
pypkgs_ash-0.1.0.dist-info/WHEEL
pypkgs_ash-0.1.0.dist-info/METADATA
pypkgs_ash-0.1.0.dist-info/RECORD
